<?xml version="1.0" encoding="UTF-8"?>
<Defs>

	<!-- Put inside production.xml -->
	<ThingDef ParentName="BenchBase">
		<defName>DankPyon_Well</defName>
		<label>well</label>
		<thingClass>Building_WorkTable</thingClass>
		<description>A small fortified hole dug through the ground to gain access to water.</description>
		<graphicData>
			<texPath>Production/Well</texPath>
			<graphicClass>Graphic_Single</graphicClass>
			<shaderType>CutoutComplex</shaderType>
			<drawSize>(3,3)</drawSize>
			<drawRotated>false</drawRotated>
		</graphicData>
		<uiIconScale>0.5</uiIconScale>
		<stuffCategories>
			<li>Stony</li>
		</stuffCategories>
		<costStuffCount>50</costStuffCount>
		<costList>
			<WoodLog>20</WoodLog>
		</costList>
		<altitudeLayer>Building</altitudeLayer>
		<fillPercent>0.5</fillPercent>
		<useHitPoints>True</useHitPoints>
		<statBases>
			<WorkToBuild>5000</WorkToBuild>
			<MaxHitPoints>120</MaxHitPoints>
			<Flammability>1.0</Flammability>
		</statBases>
		<size>(1,1)</size>
		<passability>PassThroughOnly</passability>
		<pathCost>60</pathCost>
		<hasInteractionCell>True</hasInteractionCell>
		<interactionCellOffset>(0,0,-1)</interactionCellOffset>
		<surfaceType>Item</surfaceType>
		<inspectorTabs>
			<li>ITab_Bills</li>
		</inspectorTabs>
		<designationCategory>Production</designationCategory>
		<building>
			<spawnedConceptLearnOpportunity>BillsTab</spawnedConceptLearnOpportunity>
			<isMealSource>false</isMealSource>
		</building>
		<researchPrerequisites>
			<li>DankPyon_Engineering</li>
		</researchPrerequisites>
		<terrainAffordanceNeeded>Heavy</terrainAffordanceNeeded>
	</ThingDef>

</Defs>