<?xml version="1.0" encoding="utf-8"?>
<LanguageData>

<!-- ==================== Raw Plants Resource ======================= -->  

  <DankPyon_RawFlax.label>lin</DankPyon_RawFlax.label>
  <DankPyon_RawFlax.description>Tige dotée de longues fibres végétales solides. Sa fibre peut être utilisée pour ses propriétés filandreuses et fera un bon tissu.</DankPyon_RawFlax.description>

  <DankPyon_Silkworm.label>ver à soie</DankPyon_Silkworm.label>
  <DankPyon_Silkworm.description>Petites créatures vermiformes qui produisent de la soie en créant leurs cocons. Ces derniers peuvent être récoltés pour créer de la soie fine.</DankPyon_Silkworm.description>

  <DankPyon_RawCotton.label>coton</DankPyon_RawCotton.label>
  <DankPyon_RawCotton.description>Le coton produit une fibre végétale transformée en fils, eux-mêmes transformés en tissu.</DankPyon_RawCotton.description>

  <DankPyon_RawWheat.label>blé</DankPyon_RawWheat.label>
  <DankPyon_RawWheat.description>Le blé produit un grain qui peut être moulu pour obtenir de la farine.</DankPyon_RawWheat.description>

  <DankPyon_RawGrapes.label>raisins</DankPyon_RawGrapes.label>
  <DankPyon_RawGrapes.description>Des raisins savoureux qui peuvent être consommés crus. Utile pour faire du vin.</DankPyon_RawGrapes.description>

  <DankPyon_Sugarcane.label>canne à sucre</DankPyon_Sugarcane.label>
  <DankPyon_Sugarcane.description>Canne à sucre brute. Doit être broyée en sucre pour être utilisable.</DankPyon_Sugarcane.description>

  <DankPyon_RawHerb.label>herbes</DankPyon_RawHerb.label>
  <DankPyon_RawHerb.description>Des herbes brutes.</DankPyon_RawHerb.description>

<!-- ==================== Berry Food ======================= -->

  <DankPyon_RawTomatoes.label>tomates</DankPyon_RawTomatoes.label>
  <DankPyon_RawTomatoes.description>Fruit ou légume ? En tout cas, les tomates sont très appréciées dans une multitude de plats.</DankPyon_RawTomatoes.description>

<!-- ==================== Raw Plants Food ======================= -->

  <DankPyon_RawApples.label>pommes</DankPyon_RawApples.label>
  <DankPyon_RawApples.description>Pommes brutes, très appréciées pour les desserts notamment, ou consommées crues.</DankPyon_RawApples.description>

  <DankPyon_RawLemons.label>citrons</DankPyon_RawLemons.label>
  <DankPyon_RawLemons.description>Citrons bruts, très appréciés pour agrémenter les plats par leur touche acide.</DankPyon_RawLemons.description>

  <DankPyon_RawMulberry.label>mûres</DankPyon_RawMulberry.label>
  <DankPyon_RawMulberry.description>Mûres brutes.</DankPyon_RawMulberry.description>

  <DankPyon_RawCabbages.label>choux</DankPyon_RawCabbages.label>
  <DankPyon_RawCabbages.description>Choux bruts, utilisés dans plusieurs plats.</DankPyon_RawCabbages.description>

  <DankPyon_RawCarrots.label>carottes</DankPyon_RawCarrots.label>
  <DankPyon_RawCarrots.description>Carottes brutes, utilisées dans plusieurs plats.</DankPyon_RawCarrots.description>

  <DankPyon_RawGarlic.label>ail</DankPyon_RawGarlic.label>
  <DankPyon_RawGarlic.description>Ail brute, utilisée dans plusieurs plats pour relever le goût.</DankPyon_RawGarlic.description>

  <DankPyon_RawOnions.label>oignons</DankPyon_RawOnions.label>
  <DankPyon_RawOnions.description>Oignons bruts, utilisés dans plusieurs plats.</DankPyon_RawOnions.description>

  <DankPyon_RawPumpkins.label>potirons</DankPyon_RawPumpkins.label>
  <DankPyon_RawPumpkins.description>Potirons bruts, utilisés dans plusieurs plats.</DankPyon_RawPumpkins.description>

  <DankPyon_RawLentils.label>lentilles</DankPyon_RawLentils.label>
  <DankPyon_RawLentils.description>Lentilles brutes, utilisées dans plusieurs plats. C'est une légumineuse.</DankPyon_RawLentils.description>

  <DankPyon_GriffonBerry.label>baies de griffon</DankPyon_GriffonBerry.label>
  <DankPyon_GriffonBerry.description>Baies de griffon brutes, utilisées dans les plats raffinés. Elles tirent leur nom de la créature légendaire, qui les gardait jalousement pour les consommer régulièrement.</DankPyon_GriffonBerry.description>

  <DankPyon_RawMacci.label>macci</DankPyon_RawMacci.label>
  <DankPyon_RawMacci.description>Macci utilisé comme un apport fort en protéines végétales. Remplace la viande.</DankPyon_RawMacci.description>

</LanguageData>